[{"userProfilePK":105499641,"calendarDate":"2024-03-03","deviceId":3417306097,"updateTimestamp":"2024-03-02T20:04:32.0","vo2MaxValue":53.0,"maxMet":15.200424194335938,"maxMetCategory":"GENERIC","calibratedData":0},{"userProfilePK":105499641,"calendarDate":"2024-03-03","deviceId":3417306097,"updateTimestamp":"2024-03-03T03:34:32.0","vo2MaxValue":53.0,"maxMet":15.182723999023438,"maxMetCategory":"GENERIC","calibratedData":0},{"userProfilePK":105499641,"calendarDate":"2024-03-04","deviceId":3417306097,"updateTimestamp":"2024-03-04T15:32:09.0","sport":"RUNNING","subSport":"GENERIC","vo2MaxValue":53.0,"maxMet":15.151931762695312,"maxMetCategory":"GENERIC","calibratedData":1},{"userProfilePK":105499641,"calendarDate":"2024-03-09","deviceId":3417306097,"updateTimestamp":"2024-03-09T16:53:31.0","sport":"RUNNING","subSport":"GENERIC","vo2MaxValue":53.0,"maxMet":15.130447387695312,"maxMetCategory":"GENERIC","calibratedData":1},{"userProfilePK":105499641,"calendarDate":"2024-03-13","deviceId":3417306097,"updateTimestamp":"2024-03-13T17:05:33.0","sport":"RUNNING","subSport":"GENERIC","vo2MaxValue":53.0,"maxMet":15.088653564453125,"maxMetCategory":"GENERIC","calibratedData":1},{"userProfilePK":105499641,"calendarDate":"2024-03-16","deviceId":3417306097,"updateTimestamp":"2024-03-16T16:01:27.0","sport":"RUNNING","subSport":"GENERIC","vo2MaxValue":53.0,"maxMet":15.072296142578125,"maxMetCategory":"GENERIC","calibratedData":1},{"userProfilePK":105499641,"calendarDate":"2024-03-20","deviceId":3417306097,"updateTimestamp":"2024-03-20T04:51:53.0","sport":"RUNNING","subSport":"GENERIC","vo2MaxValue":53.0,"maxMet":15.066299438476562,"maxMetCategory":"GENERIC","calibratedData":1},{"userProfilePK":105499641,"calendarDate":"2024-03-21","deviceId":3417306097,"updateTimestamp":"2024-03-21T11:36:39.0","sport":"RUNNING","subSport":"GENERIC","vo2MaxValue":53.0,"maxMet":15.1025390625,"maxMetCategory":"GENERIC","calibratedData":1},{"userProfilePK":105499641,"calendarDate":"2024-03-27","deviceId":3417306097,"updateTimestamp":"2024-03-27T15:25:02.0","sport":"RUNNING","subSport":"GENERIC","vo2MaxValue":53.0,"maxMet":15.142974853515625,"maxMetCategory":"GENERIC","calibratedData":1},{"userProfilePK":105499641,"calendarDate":"2024-03-30","deviceId":3417306097,"updateTimestamp":"2024-03-30T04:48:54.0","sport":"RUNNING","subSport":"GENERIC","vo2MaxValue":53.0,"maxMet":15.12298583984375,"maxMetCategory":"GENERIC","calibratedData":1},{"userProfilePK":105499641,"calendarDate":"2024-04-03","deviceId":3417306097,"updateTimestamp":"2024-04-03T05:02:28.0","sport":"RUNNING","subSport":"GENERIC","vo2MaxValue":53.0,"maxMet":15.151336669921875,"maxMetCategory":"GENERIC","calibratedData":1},{"userProfilePK":105499641,"calendarDate":"2024-04-06","deviceId":3417306097,"updateTimestamp":"2024-04-06T03:36:42.0","sport":"RUNNING","subSport":"GENERIC","vo2MaxValue":53.0,"maxMet":15.135711669921875,"maxMetCategory":"GENERIC","calibratedData":1},{"userProfilePK":105499641,"calendarDate":"2024-04-09","deviceId":3417306097,"updateTimestamp":"2024-04-09T14:40:44.0","sport":"RUNNING","subSport":"GENERIC","vo2MaxValue":53.0,"maxMet":15.19659423828125,"maxMetCategory":"GENERIC","calibratedData":1},{"userProfilePK":105499641,"calendarDate":"2024-04-12","deviceId":3417306097,"updateTimestamp":"2024-04-12T07:22:51.0","sport":"RUNNING","subSport":"GENERIC","vo2MaxValue":53.0,"maxMet":15.203857421875,"maxMetCategory":"GENERIC","calibratedData":1},{"userProfilePK":105499641,"calendarDate":"2024-04-14","deviceId":3417306097,"updateTimestamp":"2024-04-14T15:48:18.0","sport":"RUNNING","subSport":"GENERIC","vo2MaxValue":53.0,"maxMet":15.257858276367188,"maxMetCategory":"GENERIC","calibratedData":1},{"userProfilePK":105499641,"calendarDate":"2024-04-18","deviceId":3417306097,"updateTimestamp":"2024-04-18T14:19:39.0","sport":"RUNNING","subSport":"GENERIC","vo2MaxValue":53.0,"maxMet":15.23681640625,"maxMetCategory":"GENERIC","calibratedData":1},{"userProfilePK":105499641,"calendarDate":"2024-04-20","deviceId":3417306097,"updateTimestamp":"2024-04-20T16:15:30.0","sport":"RUNNING","subSport":"GENERIC","vo2MaxValue":53.0,"maxMet":15.19744873046875,"maxMetCategory":"GENERIC","calibratedData":1},{"userProfilePK":105499641,"calendarDate":"2024-04-26","deviceId":3417306097,"updateTimestamp":"2024-04-26T07:02:51.0","sport":"RUNNING","subSport":"GENERIC","vo2MaxValue":53.0,"maxMet":15.195556640625,"maxMetCategory":"GENERIC","calibratedData":1},{"userProfilePK":105499641,"calendarDate":"2024-05-02","deviceId":3417306097,"updateTimestamp":"2024-05-02T12:16:11.0","sport":"RUNNING","subSport":"GENERIC","vo2MaxValue":53.0,"maxMet":15.260177612304688,"maxMetCategory":"GENERIC","calibratedData":1},{"userProfilePK":105499641,"calendarDate":"2024-05-05","deviceId":3417306097,"updateTimestamp":"2024-05-05T12:11:02.0","sport":"RUNNING","subSport":"GENERIC","vo2MaxValue":53.0,"maxMet":15.20751953125,"maxMetCategory":"GENERIC","calibratedData":1},{"userProfilePK":105499641,"calendarDate":"2024-05-10","deviceId":3417306097,"updateTimestamp":"2024-05-10T07:11:15.0","sport":"CYCLING","subSport":"INDOOR_CYCLING","vo2MaxValue":55.0,"maxMet":15.76715087890625,"maxMetCategory":"CYCLING","calibratedData":1},{"userProfilePK":105499641,"calendarDate":"2024-05-10","deviceId":3417306097,"updateTimestamp":"2024-05-10T07:30:24.0","sport":"RUNNING","subSport":"GENERIC","vo2MaxValue":53.0,"maxMet":15.237991333007812,"maxMetCategory":"GENERIC","calibratedData":1},{"userProfilePK":105499641,"calendarDate":"2024-05-11","deviceId":3417306097,"updateTimestamp":"2024-05-11T16:52:54.0","sport":"RUNNING","subSport":"GENERIC","vo2MaxValue":53.0,"maxMet":15.146652221679688,"maxMetCategory":"GENERIC","calibratedData":1},{"userProfilePK":105499641,"calendarDate":"2024-05-12","deviceId":3417306097,"updateTimestamp":"2024-05-12T18:13:54.0","sport":"CYCLING","subSport":"INDOOR_CYCLING","vo2MaxValue":56.0,"maxMet":16.092514038085938,"maxMetCategory":"CYCLING","calibratedData":1},{"userProfilePK":105499641,"calendarDate":"2024-05-23","deviceId":3417306097,"updateTimestamp":"2024-05-23T14:16:32.0","sport":"RUNNING","subSport":"GENERIC","vo2MaxValue":53.0,"maxMet":15.121490478515625,"maxMetCategory":"GENERIC","calibratedData":1},{"userProfilePK":105499641,"calendarDate":"2024-05-26","deviceId":3417306097,"updateTimestamp":"2024-05-26T06:31:39.0","sport":"RUNNING","subSport":"GENERIC","vo2MaxValue":53.0,"maxMet":15.184646606445312,"maxMetCategory":"GENERIC","calibratedData":1},{"userProfilePK":105499641,"calendarDate":"2024-05-31","deviceId":3417306097,"updateTimestamp":"2024-05-31T15:55:02.0","sport":"CYCLING","subSport":"INDOOR_CYCLING","vo2MaxValue":56.0,"maxMet":16.068405151367188,"maxMetCategory":"CYCLING","calibratedData":1}]